ZCAPM/ZCAPM.py
ZCAPM/__init__.py
ZCAPM/data/ff25_day.csv
ZCAPM/data/ff_factors.csv
ZCAPM/data/ind47.csv
ZCAPM/data/mu_sigma.csv
ZCAPM-0.4.0.dist-info/LICENSE.txt
ZCAPM-0.4.0.dist-info/METADATA
ZCAPM-0.4.0.dist-info/WHEEL
ZCAPM-0.4.0.dist-info/top_level.txt
ZCAPM-0.4.0.dist-info/RECORD
